{"box_data": [{"position": {"minX": 171.375, "minY": 234.25, "maxX": 176.875, "maxY": 242.75}, "class_id": 0, "box_caption": "buoy 0.432", "scores": {"class_score": 0.43212890625}, "domain": "pixel"}, {"position": {"minX": 203.0, "minY": 233.0, "maxX": 208.0, "maxY": 241.0}, "class_id": 0, "box_caption": "buoy 0.386", "scores": {"class_score": 0.3857421875}, "domain": "pixel"}, {"position": {"minX": 170.75, "minY": 232.875, "maxX": 177.75, "maxY": 244.875}, "class_id": 0, "box_caption": "buoy 0.209", "scores": {"class_score": 0.20947265625}, "domain": "pixel"}, {"position": {"minX": 211.125, "minY": 296.75, "maxX": 218.875, "maxY": 306.75}, "class_id": 0, "box_caption": "buoy 0.192", "scores": {"class_score": 0.19189453125}, "domain": "pixel"}, {"position": {"minX": 99.6875, "minY": 233.25, "maxX": 106.5625, "maxY": 242.25}, "class_id": 0, "box_caption": "buoy 0.116", "scores": {"class_score": 0.115966796875}, "domain": "pixel"}, {"position": {"minX": 210.25, "minY": 295.5, "maxX": 221.25, "maxY": 308.5}, "class_id": 0, "box_caption": "buoy 0.112", "scores": {"class_score": 0.11199951171875}, "domain": "pixel"}, {"position": {"minX": 208.5, "minY": 294.5, "maxX": 221.75, "maxY": 310.0}, "class_id": 0, "box_caption": "buoy 0.072", "scores": {"class_score": 0.07183837890625}, "domain": "pixel"}, {"position": {"minX": 239.25, "minY": 193.125, "maxX": 245.25, "maxY": 198.125}, "class_id": 0, "box_caption": "buoy 0.066", "scores": {"class_score": 0.06634521484375}, "domain": "pixel"}, {"position": {"minX": 192.75, "minY": 194.5, "maxX": 197.75, "maxY": 201.0}, "class_id": 0, "box_caption": "buoy 0.056", "scores": {"class_score": 0.05645751953125}, "domain": "pixel"}, {"position": {"minX": 100.5, "minY": 232.625, "maxX": 108.5, "maxY": 243.625}, "class_id": 0, "box_caption": "buoy 0.051", "scores": {"class_score": 0.05145263671875}, "domain": "pixel"}, {"position": {"minX": 467.25, "minY": 184.125, "maxX": 474.25, "maxY": 190.125}, "class_id": 0, "box_caption": "buoy 0.041", "scores": {"class_score": 0.0411376953125}, "domain": "pixel"}, {"position": {"minX": 219.0, "minY": 194.25, "maxX": 223.5, "maxY": 201.25}, "class_id": 0, "box_caption": "buoy 0.040", "scores": {"class_score": 0.039947509765625}, "domain": "pixel"}, {"position": {"minX": 548.0, "minY": 177.875, "maxX": 554.0, "maxY": 184.875}, "class_id": 0, "box_caption": "buoy 0.038", "scores": {"class_score": 0.03790283203125}, "domain": "pixel"}, {"position": {"minX": 201.25, "minY": 231.25, "maxX": 209.5, "maxY": 244.75}, "class_id": 0, "box_caption": "buoy 0.037", "scores": {"class_score": 0.036773681640625}, "domain": "pixel"}, {"position": {"minX": 99.25, "minY": 231.5, "maxX": 108.25, "maxY": 245.0}, "class_id": 0, "box_caption": "buoy 0.034", "scores": {"class_score": 0.033782958984375}, "domain": "pixel"}, {"position": {"minX": 457.5, "minY": 186.125, "maxX": 462.5, "maxY": 191.375}, "class_id": 0, "box_caption": "buoy 0.032", "scores": {"class_score": 0.03240966796875}, "domain": "pixel"}, {"position": {"minX": 469.0, "minY": 184.25, "maxX": 477.0, "maxY": 191.25}, "class_id": 0, "box_caption": "buoy 0.031", "scores": {"class_score": 0.030731201171875}, "domain": "pixel"}, {"position": {"minX": 403.0, "minY": 191.25, "maxX": 410.0, "maxY": 197.5}, "class_id": 0, "box_caption": "buoy 0.028", "scores": {"class_score": 0.0282745361328125}, "domain": "pixel"}, {"position": {"minX": 602.0, "minY": 177.0, "maxX": 608.0, "maxY": 182.0}, "class_id": 0, "box_caption": "buoy 0.027", "scores": {"class_score": 0.026611328125}, "domain": "pixel"}, {"position": {"minX": 207.25, "minY": 292.0, "maxX": 221.0, "maxY": 314.0}, "class_id": 0, "box_caption": "buoy 0.026", "scores": {"class_score": 0.0259552001953125}, "domain": "pixel"}, {"position": {"minX": 167.375, "minY": 231.25, "maxX": 180.875, "maxY": 246.25}, "class_id": 0, "box_caption": "buoy 0.025", "scores": {"class_score": 0.0252227783203125}, "domain": "pixel"}, {"position": {"minX": 360.0, "minY": 198.75, "maxX": 367.0, "maxY": 205.75}, "class_id": 0, "box_caption": "buoy 0.022", "scores": {"class_score": 0.0223236083984375}, "domain": "pixel"}, {"position": {"minX": 178.0, "minY": 200.25, "maxX": 182.5, "maxY": 207.75}, "class_id": 0, "box_caption": "buoy 0.018", "scores": {"class_score": 0.0177154541015625}, "domain": "pixel"}, {"position": {"minX": 513.0, "minY": 184.25, "maxX": 519.0, "maxY": 190.25}, "class_id": 0, "box_caption": "buoy 0.017", "scores": {"class_score": 0.017303466796875}, "domain": "pixel"}, {"position": {"minX": 405.25, "minY": 191.0, "maxX": 413.25, "maxY": 198.0}, "class_id": 0, "box_caption": "buoy 0.015", "scores": {"class_score": 0.01495361328125}, "domain": "pixel"}, {"position": {"minX": 432.5, "minY": 186.75, "maxX": 437.5, "maxY": 193.25}, "class_id": 0, "box_caption": "buoy 0.015", "scores": {"class_score": 0.014617919921875}, "domain": "pixel"}, {"position": {"minX": 499.25, "minY": 183.0, "maxX": 505.75, "maxY": 189.75}, "class_id": 0, "box_caption": "buoy 0.014", "scores": {"class_score": 0.01395416259765625}, "domain": "pixel"}, {"position": {"minX": 255.75, "minY": 194.0, "maxX": 261.75, "maxY": 199.75}, "class_id": 0, "box_caption": "buoy 0.012", "scores": {"class_score": 0.01214599609375}, "domain": "pixel"}, {"position": {"minX": 168.625, "minY": 197.75, "maxX": 175.375, "maxY": 206.25}, "class_id": 0, "box_caption": "buoy 0.012", "scores": {"class_score": 0.0120086669921875}, "domain": "pixel"}, {"position": {"minX": 281.0, "minY": 192.75, "maxX": 286.0, "maxY": 197.75}, "class_id": 0, "box_caption": "buoy 0.011", "scores": {"class_score": 0.01116180419921875}, "domain": "pixel"}, {"position": {"minX": 549.5, "minY": 180.5, "maxX": 554.5, "maxY": 185.75}, "class_id": 0, "box_caption": "buoy 0.010", "scores": {"class_score": 0.00989532470703125}, "domain": "pixel"}, {"position": {"minX": 432.0, "minY": 217.125, "maxX": 439.0, "maxY": 222.125}, "class_id": 0, "box_caption": "buoy 0.009", "scores": {"class_score": 0.00864410400390625}, "domain": "pixel"}, {"position": {"minX": 489.0, "minY": 183.5, "maxX": 494.5, "maxY": 190.5}, "class_id": 0, "box_caption": "buoy 0.009", "scores": {"class_score": 0.008514404296875}, "domain": "pixel"}, {"position": {"minX": 549.0, "minY": 177.25, "maxX": 557.0, "maxY": 185.0}, "class_id": 0, "box_caption": "buoy 0.008", "scores": {"class_score": 0.007518768310546875}, "domain": "pixel"}, {"position": {"minX": 290.0, "minY": 218.0, "maxX": 296.0, "maxY": 224.5}, "class_id": 0, "box_caption": "buoy 0.007", "scores": {"class_score": 0.00731658935546875}, "domain": "pixel"}, {"position": {"minX": 407.5, "minY": 169.0, "maxX": 414.5, "maxY": 174.0}, "class_id": 0, "box_caption": "buoy 0.006", "scores": {"class_score": 0.00609588623046875}, "domain": "pixel"}, {"position": {"minX": 322.75, "minY": 194.75, "maxX": 328.25, "maxY": 203.25}, "class_id": 0, "box_caption": "buoy 0.006", "scores": {"class_score": 0.00591278076171875}, "domain": "pixel"}, {"position": {"minX": 610.0, "minY": 178.0, "maxX": 616.0, "maxY": 183.0}, "class_id": 0, "box_caption": "buoy 0.006", "scores": {"class_score": 0.00586700439453125}, "domain": "pixel"}, {"position": {"minX": 267.0, "minY": 193.375, "maxX": 273.0, "maxY": 198.375}, "class_id": 0, "box_caption": "buoy 0.006", "scores": {"class_score": 0.00586700439453125}, "domain": "pixel"}, {"position": {"minX": 165.875, "minY": 228.5, "maxX": 178.625, "maxY": 250.5}, "class_id": 0, "box_caption": "buoy 0.006", "scores": {"class_score": 0.005664825439453125}, "domain": "pixel"}, {"position": {"minX": 50.5625, "minY": 200.25, "maxX": 56.6875, "maxY": 207.25}, "class_id": 0, "box_caption": "buoy 0.006", "scores": {"class_score": 0.005641937255859375}, "domain": "pixel"}, {"position": {"minX": 194.5, "minY": 229.5, "maxX": 209.0, "maxY": 245.5}, "class_id": 0, "box_caption": "buoy 0.005", "scores": {"class_score": 0.0053863525390625}, "domain": "pixel"}, {"position": {"minX": 504.0, "minY": 184.25, "maxX": 510.5, "maxY": 191.75}, "class_id": 0, "box_caption": "buoy 0.005", "scores": {"class_score": 0.005260467529296875}, "domain": "pixel"}, {"position": {"minX": 298.5, "minY": 210.625, "maxX": 303.5, "maxY": 216.125}, "class_id": 0, "box_caption": "buoy 0.005", "scores": {"class_score": 0.005218505859375}, "domain": "pixel"}, {"position": {"minX": 314.75, "minY": 209.25, "maxX": 321.25, "maxY": 218.75}, "class_id": 0, "box_caption": "buoy 0.005", "scores": {"class_score": 0.005218505859375}, "domain": "pixel"}, {"position": {"minX": 273.25, "minY": 193.25, "maxX": 278.25, "maxY": 198.5}, "class_id": 0, "box_caption": "buoy 0.005", "scores": {"class_score": 0.00518035888671875}, "domain": "pixel"}, {"position": {"minX": 498.75, "minY": 179.25, "maxX": 505.25, "maxY": 187.25}, "class_id": 0, "box_caption": "buoy 0.005", "scores": {"class_score": 0.005062103271484375}, "domain": "pixel"}, {"position": {"minX": 488.5, "minY": 231.25, "maxX": 494.5, "maxY": 238.75}, "class_id": 0, "box_caption": "buoy 0.005", "scores": {"class_score": 0.00498199462890625}, "domain": "pixel"}, {"position": {"minX": 208.0, "minY": 290.0, "maxX": 221.5, "maxY": 309.0}, "class_id": 0, "box_caption": "buoy 0.005", "scores": {"class_score": 0.004962921142578125}, "domain": "pixel"}, {"position": {"minX": 235.25, "minY": 192.25, "maxX": 246.0, "maxY": 199.75}, "class_id": 0, "box_caption": "buoy 0.005", "scores": {"class_score": 0.00490570068359375}, "domain": "pixel"}, {"position": {"minX": 432.0, "minY": 187.5, "maxX": 438.5, "maxY": 197.0}, "class_id": 0, "box_caption": "buoy 0.005", "scores": {"class_score": 0.004718780517578125}, "domain": "pixel"}, {"position": {"minX": 217.75, "minY": 194.625, "maxX": 223.75, "maxY": 205.125}, "class_id": 0, "box_caption": "buoy 0.005", "scores": {"class_score": 0.004718780517578125}, "domain": "pixel"}, {"position": {"minX": 251.0, "minY": 193.25, "maxX": 258.5, "maxY": 200.25}, "class_id": 0, "box_caption": "buoy 0.005", "scores": {"class_score": 0.004520416259765625}, "domain": "pixel"}, {"position": {"minX": 427.0, "minY": 187.0, "maxX": 435.0, "maxY": 197.5}, "class_id": 0, "box_caption": "buoy 0.004", "scores": {"class_score": 0.004467010498046875}, "domain": "pixel"}, {"position": {"minX": 359.5, "minY": 194.875, "maxX": 366.5, "maxY": 204.375}, "class_id": 0, "box_caption": "buoy 0.004", "scores": {"class_score": 0.00394439697265625}, "domain": "pixel"}, {"position": {"minX": 469.0, "minY": 183.5, "maxX": 474.0, "maxY": 189.75}, "class_id": 0, "box_caption": "buoy 0.004", "scores": {"class_score": 0.00391387939453125}, "domain": "pixel"}, {"position": {"minX": 198.75, "minY": 230.5, "maxX": 212.75, "maxY": 244.5}, "class_id": 0, "box_caption": "buoy 0.004", "scores": {"class_score": 0.0038852691650390625}, "domain": "pixel"}, {"position": {"minX": 402.5, "minY": 187.0, "maxX": 411.5, "maxY": 197.0}, "class_id": 0, "box_caption": "buoy 0.004", "scores": {"class_score": 0.0037078857421875}, "domain": "pixel"}, {"position": {"minX": 546.0, "minY": 177.125, "maxX": 556.0, "maxY": 189.125}, "class_id": 0, "box_caption": "buoy 0.004", "scores": {"class_score": 0.0037078857421875}, "domain": "pixel"}, {"position": {"minX": 322.5, "minY": 195.875, "maxX": 328.0, "maxY": 205.875}, "class_id": 0, "box_caption": "buoy 0.004", "scores": {"class_score": 0.0035381317138671875}, "domain": "pixel"}, {"position": {"minX": 427.5, "minY": 186.0, "maxX": 436.5, "maxY": 195.5}, "class_id": 0, "box_caption": "buoy 0.003", "scores": {"class_score": 0.003482818603515625}, "domain": "pixel"}, {"position": {"minX": 506.75, "minY": 190.25, "maxX": 511.75, "maxY": 198.25}, "class_id": 0, "box_caption": "buoy 0.003", "scores": {"class_score": 0.0034694671630859375}, "domain": "pixel"}, {"position": {"minX": 456.0, "minY": 231.0, "maxX": 461.5, "maxY": 241.0}, "class_id": 0, "box_caption": "buoy 0.003", "scores": {"class_score": 0.0032596588134765625}, "domain": "pixel"}, {"position": {"minX": 311.0, "minY": 231.0, "maxX": 318.0, "maxY": 238.0}, "class_id": 0, "box_caption": "buoy 0.003", "scores": {"class_score": 0.00319671630859375}, "domain": "pixel"}, {"position": {"minX": 91.0625, "minY": 199.875, "maxX": 95.9375, "maxY": 205.875}, "class_id": 0, "box_caption": "buoy 0.003", "scores": {"class_score": 0.003185272216796875}, "domain": "pixel"}, {"position": {"minX": 168.0, "minY": 195.0, "maxX": 174.5, "maxY": 206.0}, "class_id": 0, "box_caption": "buoy 0.003", "scores": {"class_score": 0.00313568115234375}, "domain": "pixel"}, {"position": {"minX": 343.75, "minY": 198.0, "maxX": 350.25, "maxY": 206.0}, "class_id": 0, "box_caption": "buoy 0.003", "scores": {"class_score": 0.0030269622802734375}, "domain": "pixel"}, {"position": {"minX": 520.0, "minY": 182.0, "maxX": 526.0, "maxY": 190.5}, "class_id": 0, "box_caption": "buoy 0.003", "scores": {"class_score": 0.0029354095458984375}, "domain": "pixel"}, {"position": {"minX": 146.5, "minY": 214.5, "maxX": 153.0, "maxY": 222.0}, "class_id": 0, "box_caption": "buoy 0.003", "scores": {"class_score": 0.00284576416015625}, "domain": "pixel"}, {"position": {"minX": 616.0, "minY": 177.5, "maxX": 622.0, "maxY": 183.0}, "class_id": 0, "box_caption": "buoy 0.003", "scores": {"class_score": 0.002834320068359375}, "domain": "pixel"}, {"position": {"minX": 192.25, "minY": 194.25, "maxX": 199.25, "maxY": 205.25}, "class_id": 0, "box_caption": "buoy 0.003", "scores": {"class_score": 0.00269317626953125}, "domain": "pixel"}, {"position": {"minX": 502.0, "minY": 182.75, "maxX": 506.0, "maxY": 187.75}, "class_id": 0, "box_caption": "buoy 0.003", "scores": {"class_score": 0.002620697021484375}, "domain": "pixel"}, {"position": {"minX": 215.0, "minY": 198.25, "maxX": 220.5, "maxY": 201.75}, "class_id": 0, "box_caption": "buoy 0.003", "scores": {"class_score": 0.0025310516357421875}, "domain": "pixel"}, {"position": {"minX": 354.75, "minY": 196.375, "maxX": 366.75, "maxY": 207.625}, "class_id": 0, "box_caption": "buoy 0.003", "scores": {"class_score": 0.0025119781494140625}, "domain": "pixel"}, {"position": {"minX": 205.875, "minY": 289.0, "maxX": 222.625, "maxY": 311.0}, "class_id": 0, "box_caption": "buoy 0.002", "scores": {"class_score": 0.0024929046630859375}, "domain": "pixel"}, {"position": {"minX": 186.75, "minY": 229.625, "maxX": 192.5, "maxY": 238.125}, "class_id": 0, "box_caption": "buoy 0.002", "scores": {"class_score": 0.0022525787353515625}, "domain": "pixel"}, {"position": {"minX": 167.25, "minY": 198.25, "maxX": 174.75, "maxY": 206.0}, "class_id": 0, "box_caption": "buoy 0.002", "scores": {"class_score": 0.0021820068359375}, "domain": "pixel"}, {"position": {"minX": 497.5, "minY": 208.5, "maxX": 503.5, "maxY": 217.0}, "class_id": 0, "box_caption": "buoy 0.002", "scores": {"class_score": 0.0021572113037109375}, "domain": "pixel"}, {"position": {"minX": 162.625, "minY": 230.5, "maxX": 178.375, "maxY": 248.0}, "class_id": 0, "box_caption": "buoy 0.002", "scores": {"class_score": 0.0021076202392578125}, "domain": "pixel"}, {"position": {"minX": 582.5, "minY": 201.375, "maxX": 589.5, "maxY": 208.375}, "class_id": 0, "box_caption": "buoy 0.002", "scores": {"class_score": 0.001972198486328125}, "domain": "pixel"}, {"position": {"minX": 97.875, "minY": 231.75, "maxX": 107.875, "maxY": 249.25}, "class_id": 0, "box_caption": "buoy 0.002", "scores": {"class_score": 0.001972198486328125}, "domain": "pixel"}, {"position": {"minX": 612.0, "minY": 180.875, "maxX": 618.0, "maxY": 185.875}, "class_id": 0, "box_caption": "buoy 0.002", "scores": {"class_score": 0.0019044876098632812}, "domain": "pixel"}, {"position": {"minX": 210.125, "minY": 194.5, "maxX": 215.625, "maxY": 206.0}, "class_id": 0, "box_caption": "buoy 0.002", "scores": {"class_score": 0.0018968582153320312}, "domain": "pixel"}, {"position": {"minX": 209.25, "minY": 193.75, "maxX": 215.25, "maxY": 203.75}, "class_id": 0, "box_caption": "buoy 0.002", "scores": {"class_score": 0.0018529891967773438}, "domain": "pixel"}, {"position": {"minX": 598.0, "minY": 177.125, "maxX": 608.0, "maxY": 186.125}, "class_id": 0, "box_caption": "buoy 0.002", "scores": {"class_score": 0.0018463134765625}, "domain": "pixel"}, {"position": {"minX": 202.375, "minY": 193.5, "maxX": 207.625, "maxY": 203.5}, "class_id": 0, "box_caption": "buoy 0.002", "scores": {"class_score": 0.0018310546875}, "domain": "pixel"}, {"position": {"minX": 201.5, "minY": 291.0, "maxX": 221.0, "maxY": 313.0}, "class_id": 0, "box_caption": "buoy 0.002", "scores": {"class_score": 0.0017480850219726562}, "domain": "pixel"}, {"position": {"minX": 197.0, "minY": 226.875, "maxX": 210.0, "maxY": 250.375}, "class_id": 0, "box_caption": "buoy 0.002", "scores": {"class_score": 0.0017271041870117188}, "domain": "pixel"}, {"position": {"minX": 198.25, "minY": 198.125, "maxX": 201.75, "maxY": 201.875}, "class_id": 0, "box_caption": "buoy 0.002", "scores": {"class_score": 0.001720428466796875}, "domain": "pixel"}, {"position": {"minX": 202.75, "minY": 195.75, "maxX": 208.75, "maxY": 205.75}, "class_id": 0, "box_caption": "buoy 0.002", "scores": {"class_score": 0.0016870498657226562}, "domain": "pixel"}, {"position": {"minX": 579.5, "minY": 201.75, "maxX": 586.5, "maxY": 208.75}, "class_id": 0, "box_caption": "buoy 0.002", "scores": {"class_score": 0.001628875732421875}, "domain": "pixel"}, {"position": {"minX": 166.25, "minY": 230.25, "maxX": 177.75, "maxY": 245.25}, "class_id": 0, "box_caption": "buoy 0.002", "scores": {"class_score": 0.0016040802001953125}, "domain": "pixel"}, {"position": {"minX": 549.5, "minY": 179.5, "maxX": 558.5, "maxY": 189.5}, "class_id": 0, "box_caption": "buoy 0.002", "scores": {"class_score": 0.0015850067138671875}, "domain": "pixel"}, {"position": {"minX": 150.25, "minY": 212.75, "maxX": 155.75, "maxY": 218.75}, "class_id": 0, "box_caption": "buoy 0.002", "scores": {"class_score": 0.0015850067138671875}, "domain": "pixel"}, {"position": {"minX": 518.0, "minY": 183.0, "maxX": 522.0, "maxY": 188.0}, "class_id": 0, "box_caption": "buoy 0.002", "scores": {"class_score": 0.00157928466796875}, "domain": "pixel"}, {"position": {"minX": 405.5, "minY": 162.75, "maxX": 414.5, "maxY": 169.75}, "class_id": 0, "box_caption": "buoy 0.002", "scores": {"class_score": 0.0015735626220703125}, "domain": "pixel"}, {"position": {"minX": 465.5, "minY": 179.375, "maxX": 474.0, "maxY": 190.625}, "class_id": 0, "box_caption": "buoy 0.002", "scores": {"class_score": 0.0015611648559570312}, "domain": "pixel"}, {"position": {"minX": 313.5, "minY": 208.625, "maxX": 321.5, "maxY": 221.875}, "class_id": 0, "box_caption": "buoy 0.001", "scores": {"class_score": 0.0014553070068359375}, "domain": "pixel"}, {"position": {"minX": 70.875, "minY": 249.75, "maxX": 77.75, "maxY": 256.75}, "class_id": 0, "box_caption": "buoy 0.001", "scores": {"class_score": 0.0014104843139648438}, "domain": "pixel"}, {"position": {"minX": 482.5, "minY": 183.25, "maxX": 492.0, "maxY": 190.75}, "class_id": 0, "box_caption": "buoy 0.001", "scores": {"class_score": 0.0013990402221679688}, "domain": "pixel"}, {"position": {"minX": 166.5, "minY": 230.25, "maxX": 182.5, "maxY": 254.25}, "class_id": 0, "box_caption": "buoy 0.001", "scores": {"class_score": 0.0013885498046875}, "domain": "pixel"}, {"position": {"minX": 607.5, "minY": 136.75, "maxX": 614.5, "maxY": 142.75}, "class_id": 0, "box_caption": "buoy 0.001", "scores": {"class_score": 0.001361846923828125}, "domain": "pixel"}, {"position": {"minX": 146.375, "minY": 210.5, "maxX": 153.625, "maxY": 218.5}, "class_id": 0, "box_caption": "buoy 0.001", "scores": {"class_score": 0.0013513565063476562}, "domain": "pixel"}, {"position": {"minX": 359.0, "minY": 199.0, "maxX": 366.0, "maxY": 203.75}, "class_id": 0, "box_caption": "buoy 0.001", "scores": {"class_score": 0.0013456344604492188}, "domain": "pixel"}, {"position": {"minX": 167.5, "minY": 226.75, "maxX": 179.5, "maxY": 246.75}, "class_id": 0, "box_caption": "buoy 0.001", "scores": {"class_score": 0.0013093948364257812}, "domain": "pixel"}, {"position": {"minX": 406.75, "minY": 186.5, "maxX": 414.25, "maxY": 195.5}, "class_id": 0, "box_caption": "buoy 0.001", "scores": {"class_score": 0.001239776611328125}, "domain": "pixel"}, {"position": {"minX": 199.0, "minY": 224.875, "maxX": 208.5, "maxY": 241.625}, "class_id": 0, "box_caption": "buoy 0.001", "scores": {"class_score": 0.001239776611328125}, "domain": "pixel"}, {"position": {"minX": 325.25, "minY": 197.75, "maxX": 329.25, "maxY": 202.75}, "class_id": 0, "box_caption": "buoy 0.001", "scores": {"class_score": 0.0012302398681640625}, "domain": "pixel"}, {"position": {"minX": 450.25, "minY": 185.0, "maxX": 464.25, "maxY": 192.5}, "class_id": 0, "box_caption": "buoy 0.001", "scores": {"class_score": 0.0011968612670898438}, "domain": "pixel"}, {"position": {"minX": 186.5, "minY": 192.0, "maxX": 199.0, "maxY": 206.0}, "class_id": 0, "box_caption": "buoy 0.001", "scores": {"class_score": 0.001155853271484375}, "domain": "pixel"}, {"position": {"minX": 343.25, "minY": 194.125, "maxX": 350.75, "maxY": 205.125}, "class_id": 0, "box_caption": "buoy 0.001", "scores": {"class_score": 0.0011157989501953125}, "domain": "pixel"}, {"position": {"minX": 121.875, "minY": 201.0, "maxX": 127.625, "maxY": 207.5}, "class_id": 0, "box_caption": "buoy 0.001", "scores": {"class_score": 0.001056671142578125}, "domain": "pixel"}, {"position": {"minX": 601.0, "minY": 176.25, "maxX": 610.0, "maxY": 189.75}, "class_id": 0, "box_caption": "buoy 0.001", "scores": {"class_score": 0.0010366439819335938}, "domain": "pixel"}, {"position": {"minX": 288.25, "minY": 219.0, "maxX": 296.25, "maxY": 229.5}, "class_id": 0, "box_caption": "buoy 0.001", "scores": {"class_score": 0.0010280609130859375}, "domain": "pixel"}], "class_labels": {"0": "buoy"}}