{"box_data": [{"position": {"minX": 170.25, "minY": 234.375, "maxX": 178.75, "maxY": 245.125}, "class_id": 0, "box_caption": "buoy 0.255", "scores": {"class_score": 0.25537109375}, "domain": "pixel"}, {"position": {"minX": 202.5, "minY": 230.5, "maxX": 209.0, "maxY": 241.5}, "class_id": 0, "box_caption": "buoy 0.246", "scores": {"class_score": 0.245849609375}, "domain": "pixel"}, {"position": {"minX": 208.75, "minY": 296.0, "maxX": 220.25, "maxY": 311.0}, "class_id": 0, "box_caption": "buoy 0.082", "scores": {"class_score": 0.08209228515625}, "domain": "pixel"}, {"position": {"minX": 203.875, "minY": 291.5, "maxX": 222.625, "maxY": 315.5}, "class_id": 0, "box_caption": "buoy 0.071", "scores": {"class_score": 0.07080078125}, "domain": "pixel"}, {"position": {"minX": 101.125, "minY": 233.5, "maxX": 108.5, "maxY": 242.5}, "class_id": 0, "box_caption": "buoy 0.054", "scores": {"class_score": 0.0535888671875}, "domain": "pixel"}, {"position": {"minX": 99.75, "minY": 232.75, "maxX": 106.75, "maxY": 242.0}, "class_id": 0, "box_caption": "buoy 0.052", "scores": {"class_score": 0.05242919921875}, "domain": "pixel"}, {"position": {"minX": 99.375, "minY": 230.375, "maxX": 107.125, "maxY": 242.625}, "class_id": 0, "box_caption": "buoy 0.051", "scores": {"class_score": 0.05108642578125}, "domain": "pixel"}, {"position": {"minX": 167.75, "minY": 232.0, "maxX": 181.0, "maxY": 246.0}, "class_id": 0, "box_caption": "buoy 0.049", "scores": {"class_score": 0.049041748046875}, "domain": "pixel"}, {"position": {"minX": 147.5, "minY": 214.0, "maxX": 155.0, "maxY": 219.0}, "class_id": 0, "box_caption": "buoy 0.033", "scores": {"class_score": 0.03271484375}, "domain": "pixel"}, {"position": {"minX": 147.25, "minY": 215.75, "maxX": 154.25, "maxY": 221.25}, "class_id": 0, "box_caption": "buoy 0.031", "scores": {"class_score": 0.030792236328125}, "domain": "pixel"}, {"position": {"minX": 200.5, "minY": 230.5, "maxX": 210.0, "maxY": 245.0}, "class_id": 0, "box_caption": "buoy 0.029", "scores": {"class_score": 0.0292510986328125}, "domain": "pixel"}, {"position": {"minX": 72.0, "minY": 249.375, "maxX": 77.5, "maxY": 255.625}, "class_id": 0, "box_caption": "buoy 0.029", "scores": {"class_score": 0.0290374755859375}, "domain": "pixel"}, {"position": {"minX": 98.3125, "minY": 233.0, "maxX": 108.1875, "maxY": 245.0}, "class_id": 0, "box_caption": "buoy 0.018", "scores": {"class_score": 0.018402099609375}, "domain": "pixel"}, {"position": {"minX": 199.5, "minY": 230.25, "maxX": 213.0, "maxY": 243.25}, "class_id": 0, "box_caption": "buoy 0.015", "scores": {"class_score": 0.01519012451171875}, "domain": "pixel"}, {"position": {"minX": 118.5, "minY": 250.5, "maxX": 126.0, "maxY": 258.0}, "class_id": 0, "box_caption": "buoy 0.013", "scores": {"class_score": 0.013427734375}, "domain": "pixel"}, {"position": {"minX": 471.5, "minY": 270.5, "maxX": 477.5, "maxY": 278.0}, "class_id": 0, "box_caption": "buoy 0.013", "scores": {"class_score": 0.0125274658203125}, "domain": "pixel"}, {"position": {"minX": 322.25, "minY": 603.0, "maxX": 374.25, "maxY": 657.0}, "class_id": 0, "box_caption": "buoy 0.012", "scores": {"class_score": 0.012237548828125}, "domain": "pixel"}, {"position": {"minX": 199.625, "minY": 283.0, "maxX": 225.125, "maxY": 319.0}, "class_id": 0, "box_caption": "buoy 0.012", "scores": {"class_score": 0.0118255615234375}, "domain": "pixel"}, {"position": {"minX": 212.25, "minY": 197.375, "maxX": 219.25, "maxY": 204.625}, "class_id": 0, "box_caption": "buoy 0.010", "scores": {"class_score": 0.0103302001953125}, "domain": "pixel"}, {"position": {"minX": 150.5, "minY": 215.875, "maxX": 157.0, "maxY": 221.125}, "class_id": 0, "box_caption": "buoy 0.010", "scores": {"class_score": 0.00955963134765625}, "domain": "pixel"}, {"position": {"minX": 204.0, "minY": 290.25, "maxX": 225.5, "maxY": 321.75}, "class_id": 0, "box_caption": "buoy 0.010", "scores": {"class_score": 0.009521484375}, "domain": "pixel"}, {"position": {"minX": 135.5, "minY": 216.125, "maxX": 141.5, "maxY": 221.375}, "class_id": 0, "box_caption": "buoy 0.008", "scores": {"class_score": 0.0082550048828125}, "domain": "pixel"}, {"position": {"minX": 131.25, "minY": 215.875, "maxX": 138.0, "maxY": 221.125}, "class_id": 0, "box_caption": "buoy 0.007", "scores": {"class_score": 0.006641387939453125}, "domain": "pixel"}, {"position": {"minX": 67.875, "minY": 246.25, "maxX": 75.875, "maxY": 254.25}, "class_id": 0, "box_caption": "buoy 0.006", "scores": {"class_score": 0.00591278076171875}, "domain": "pixel"}, {"position": {"minX": 131.0, "minY": 214.125, "maxX": 139.5, "maxY": 219.625}, "class_id": 0, "box_caption": "buoy 0.005", "scores": {"class_score": 0.0054473876953125}, "domain": "pixel"}, {"position": {"minX": 122.0, "minY": 216.25, "maxX": 127.0, "maxY": 221.25}, "class_id": 0, "box_caption": "buoy 0.005", "scores": {"class_score": 0.0053863525390625}, "domain": "pixel"}, {"position": {"minX": 123.0, "minY": 233.75, "maxX": 127.5, "maxY": 238.25}, "class_id": 0, "box_caption": "buoy 0.005", "scores": {"class_score": 0.005344390869140625}, "domain": "pixel"}, {"position": {"minX": 197.75, "minY": 228.75, "maxX": 214.0, "maxY": 246.25}, "class_id": 0, "box_caption": "buoy 0.004", "scores": {"class_score": 0.004364013671875}, "domain": "pixel"}, {"position": {"minX": 193.75, "minY": 194.5, "maxX": 198.75, "maxY": 201.0}, "class_id": 0, "box_caption": "buoy 0.004", "scores": {"class_score": 0.004299163818359375}, "domain": "pixel"}, {"position": {"minX": 90.3125, "minY": 232.625, "maxX": 94.8125, "maxY": 238.625}, "class_id": 0, "box_caption": "buoy 0.004", "scores": {"class_score": 0.004199981689453125}, "domain": "pixel"}, {"position": {"minX": 361.75, "minY": 264.0, "maxX": 370.75, "maxY": 271.0}, "class_id": 0, "box_caption": "buoy 0.004", "scores": {"class_score": 0.00395965576171875}, "domain": "pixel"}, {"position": {"minX": 176.875, "minY": 202.0, "maxX": 182.375, "maxY": 209.0}, "class_id": 0, "box_caption": "buoy 0.004", "scores": {"class_score": 0.00392913818359375}, "domain": "pixel"}, {"position": {"minX": 117.4375, "minY": 252.0, "maxX": 126.4375, "maxY": 261.0}, "class_id": 0, "box_caption": "buoy 0.004", "scores": {"class_score": 0.00392913818359375}, "domain": "pixel"}, {"position": {"minX": 218.125, "minY": 199.5, "maxX": 223.625, "maxY": 205.25}, "class_id": 0, "box_caption": "buoy 0.004", "scores": {"class_score": 0.0037212371826171875}, "domain": "pixel"}, {"position": {"minX": 49.1875, "minY": 233.75, "maxX": 53.9375, "maxY": 237.75}, "class_id": 0, "box_caption": "buoy 0.003", "scores": {"class_score": 0.0034160614013671875}, "domain": "pixel"}, {"position": {"minX": 96.25, "minY": 216.625, "maxX": 101.5, "maxY": 221.375}, "class_id": 0, "box_caption": "buoy 0.003", "scores": {"class_score": 0.003223419189453125}, "domain": "pixel"}, {"position": {"minX": 67.125, "minY": 248.25, "maxX": 74.875, "maxY": 255.75}, "class_id": 0, "box_caption": "buoy 0.003", "scores": {"class_score": 0.00319671630859375}, "domain": "pixel"}, {"position": {"minX": 91.125, "minY": 216.0, "maxX": 98.0, "maxY": 221.25}, "class_id": 0, "box_caption": "buoy 0.003", "scores": {"class_score": 0.003124237060546875}, "domain": "pixel"}, {"position": {"minX": 170.0, "minY": 216.375, "maxX": 175.0, "maxY": 221.375}, "class_id": 0, "box_caption": "buoy 0.003", "scores": {"class_score": 0.002620697021484375}, "domain": "pixel"}, {"position": {"minX": 197.0, "minY": 228.375, "maxX": 206.0, "maxY": 245.125}, "class_id": 0, "box_caption": "buoy 0.003", "scores": {"class_score": 0.0025501251220703125}, "domain": "pixel"}, {"position": {"minX": 218.0, "minY": 194.75, "maxX": 224.0, "maxY": 202.25}, "class_id": 0, "box_caption": "buoy 0.002", "scores": {"class_score": 0.0023593902587890625}, "domain": "pixel"}, {"position": {"minX": 165.375, "minY": 229.0, "maxX": 183.125, "maxY": 250.0}, "class_id": 0, "box_caption": "buoy 0.002", "scores": {"class_score": 0.0023326873779296875}, "domain": "pixel"}, {"position": {"minX": 151.5, "minY": 210.625, "maxX": 158.0, "maxY": 216.625}, "class_id": 0, "box_caption": "buoy 0.002", "scores": {"class_score": 0.002323150634765625}, "domain": "pixel"}, {"position": {"minX": 200.75, "minY": 226.5, "maxX": 209.25, "maxY": 242.0}, "class_id": 0, "box_caption": "buoy 0.002", "scores": {"class_score": 0.0023059844970703125}, "domain": "pixel"}, {"position": {"minX": 82.625, "minY": 233.625, "maxX": 86.375, "maxY": 238.125}, "class_id": 0, "box_caption": "buoy 0.002", "scores": {"class_score": 0.0022602081298828125}, "domain": "pixel"}, {"position": {"minX": 97.25, "minY": 230.875, "maxX": 113.25, "maxY": 249.875}, "class_id": 0, "box_caption": "buoy 0.002", "scores": {"class_score": 0.0021152496337890625}, "domain": "pixel"}, {"position": {"minX": 297.0, "minY": 213.5, "maxX": 305.0, "maxY": 223.0}, "class_id": 0, "box_caption": "buoy 0.002", "scores": {"class_score": 0.001941680908203125}, "domain": "pixel"}, {"position": {"minX": 128.5, "minY": 233.75, "maxX": 133.5, "maxY": 237.75}, "class_id": 0, "box_caption": "buoy 0.002", "scores": {"class_score": 0.0018749237060546875}, "domain": "pixel"}, {"position": {"minX": 4.75, "minY": 89.5, "maxX": 327.25, "maxY": 666.0}, "class_id": 0, "box_caption": "buoy 0.002", "scores": {"class_score": 0.0018310546875}, "domain": "pixel"}, {"position": {"minX": 114.375, "minY": 233.0, "maxX": 119.125, "maxY": 238.5}, "class_id": 0, "box_caption": "buoy 0.002", "scores": {"class_score": 0.0017824172973632812}, "domain": "pixel"}, {"position": {"minX": 115.0, "minY": 249.25, "maxX": 126.5, "maxY": 258.75}, "class_id": 0, "box_caption": "buoy 0.002", "scores": {"class_score": 0.0016613006591796875}, "domain": "pixel"}, {"position": {"minX": 64.25, "minY": 293.0, "maxX": 91.25, "maxY": 325.5}, "class_id": 0, "box_caption": "buoy 0.002", "scores": {"class_score": 0.0015850067138671875}, "domain": "pixel"}, {"position": {"minX": 185.75, "minY": 231.0, "maxX": 191.25, "maxY": 239.0}, "class_id": 0, "box_caption": "buoy 0.002", "scores": {"class_score": 0.001506805419921875}, "domain": "pixel"}, {"position": {"minX": 489.5, "minY": 207.5, "maxX": 495.5, "maxY": 214.5}, "class_id": 0, "box_caption": "buoy 0.001", "scores": {"class_score": 0.0014781951904296875}, "domain": "pixel"}, {"position": {"minX": 203.25, "minY": 276.0, "maxX": 239.25, "maxY": 324.0}, "class_id": 0, "box_caption": "buoy 0.001", "scores": {"class_score": 0.0014667510986328125}, "domain": "pixel"}, {"position": {"minX": 170.375, "minY": 201.0, "maxX": 176.625, "maxY": 208.5}, "class_id": 0, "box_caption": "buoy 0.001", "scores": {"class_score": 0.0014495849609375}, "domain": "pixel"}, {"position": {"minX": 196.25, "minY": 206.25, "maxX": 205.75, "maxY": 219.25}, "class_id": 0, "box_caption": "buoy 0.001", "scores": {"class_score": 0.0013780593872070312}, "domain": "pixel"}, {"position": {"minX": 186.0, "minY": 216.625, "maxX": 190.5, "maxY": 221.375}, "class_id": 0, "box_caption": "buoy 0.001", "scores": {"class_score": 0.0012941360473632812}, "domain": "pixel"}, {"position": {"minX": 623.0, "minY": 434.5, "maxX": 659.0, "maxY": 626.5}, "class_id": 0, "box_caption": "buoy 0.001", "scores": {"class_score": 0.0012598037719726562}, "domain": "pixel"}, {"position": {"minX": 164.125, "minY": 228.75, "maxX": 180.125, "maxY": 246.25}, "class_id": 0, "box_caption": "buoy 0.001", "scores": {"class_score": 0.0012063980102539062}, "domain": "pixel"}, {"position": {"minX": 203.75, "minY": 225.25, "maxX": 214.75, "maxY": 235.25}, "class_id": 0, "box_caption": "buoy 0.001", "scores": {"class_score": 0.001201629638671875}, "domain": "pixel"}, {"position": {"minX": 146.875, "minY": 210.75, "maxX": 154.875, "maxY": 218.75}, "class_id": 0, "box_caption": "buoy 0.001", "scores": {"class_score": 0.0011968612670898438}, "domain": "pixel"}, {"position": {"minX": 201.875, "minY": 217.25, "maxX": 206.125, "maxY": 222.25}, "class_id": 0, "box_caption": "buoy 0.001", "scores": {"class_score": 0.0011968612670898438}, "domain": "pixel"}, {"position": {"minX": 577.0, "minY": 166.25, "maxX": 601.0, "maxY": 212.25}, "class_id": 0, "box_caption": "buoy 0.001", "scores": {"class_score": 0.0011920928955078125}, "domain": "pixel"}, {"position": {"minX": 290.5, "minY": 216.75, "maxX": 295.5, "maxY": 225.0}, "class_id": 0, "box_caption": "buoy 0.001", "scores": {"class_score": 0.0011653900146484375}, "domain": "pixel"}, {"position": {"minX": 471.0, "minY": 265.5, "maxX": 478.5, "maxY": 276.5}, "class_id": 0, "box_caption": "buoy 0.001", "scores": {"class_score": 0.0011243820190429688}, "domain": "pixel"}, {"position": {"minX": 279.75, "minY": 202.5, "maxX": 286.75, "maxY": 209.0}, "class_id": 0, "box_caption": "buoy 0.001", "scores": {"class_score": 0.0011119842529296875}, "domain": "pixel"}, {"position": {"minX": 194.0, "minY": 200.625, "maxX": 199.25, "maxY": 205.625}, "class_id": 0, "box_caption": "buoy 0.001", "scores": {"class_score": 0.0010528564453125}, "domain": "pixel"}, {"position": {"minX": 192.75, "minY": 273.0, "maxX": 224.5, "maxY": 319.0}, "class_id": 0, "box_caption": "buoy 0.001", "scores": {"class_score": 0.0010366439819335938}, "domain": "pixel"}, {"position": {"minX": 190.75, "minY": 227.0, "maxX": 211.5, "maxY": 251.0}, "class_id": 0, "box_caption": "buoy 0.001", "scores": {"class_score": 0.0010080337524414062}, "domain": "pixel"}], "class_labels": {"0": "buoy"}}